<?xml version="1.0" encoding="utf-8"?>
<annotation>
<folder>images</folder>
<filename>2e40f4fe-Black-chinned_Hummingbird_Arizona_01.jpg</filename>
<source>
<database>MyDatabase</database>
<annotation>COCO2017</annotation>
<image>flickr</image>
<flickrid>NULL</flickrid>
<annotator>1</annotator>
</source>
<owner>
<flickrid>NULL</flickrid>
<name>Label Studio</name>
</owner>
<size>
<width>2643</width>
<height>1852</height>
<depth>3</depth>
</size>
<segmented>0</segmented>
<object>
<name>archilochus alexandri</name>
<pose>Unspecified</pose>
<truncated>0</truncated>
<difficult>0</difficult>
<bndbox>
<xmin>275</xmin>
<ymin>397</ymin>
<xmax>2182</xmax>
<ymax>1633</ymax>
</bndbox>
</object>
</annotation>
